{
    "regular": {
        "2015": [
            {
                "month": "January",
                "year": 2015,
                "price": 41.41
            },
            {
                "month": "February",
                "year": 2015,
                "price": 47.9
            },
            {
                "month": "March",
                "year": 2015,
                "price": 44.08
            },
            {
                "month": "April",
                "year": 2015,
                "price": 46.35
            },
            {
                "month": "May",
                "year": 2015,
                "price": 34.43
            },
            {
                "month": "June",
                "year": 2015,
                "price": 43.11
            },
            {
                "month": "July",
                "year": 2015,
                "price": 36.49
            },
            {
                "month": "August",
                "year": 2015,
                "price": 75.47
            },
            {
                "month": "September",
                "year": 2015,
                "price": 68.52
            },
            {
                "month": "October",
                "year": 2015,
                "price": 69.54
            },
            {
                "month": "November",
                "year": 2015,
                "price": 68.37
            },
            {
                "month": "December",
                "year": 2015,
                "price": 53.8
            }
        ],
        "2016": [
            {
                "month": "January",
                "year": 2016,
                "price": 57.4
            },
            {
                "month": "February",
                "year": 2016,
                "price": 79.99
            },
            {
                "month": "March",
                "year": 2016,
                "price": 67.85
            },
            {
                "month": "April",
                "year": 2016,
                "price": 67.84
            },
            {
                "month": "May",
                "year": 2016,
                "price": 73.19
            },
            {
                "month": "June",
                "year": 2016,
                "price": 64.87
            },
            {
                "month": "July",
                "year": 2016,
                "price": 73.96
            },
            {
                "month": "August",
                "year": 2016,
                "price": 49.55
            },
            {
                "month": "September",
                "year": 2016,
                "price": 46.04
            },
            {
                "month": "October",
                "year": 2016,
                "price": 45.39
            },
            {
                "month": "November",
                "year": 2016,
                "price": 56.1
            },
            {
                "month": "December",
                "year": 2016,
                "price": 73.73
            }
        ],
        "2017": [
            {
                "month": "January",
                "year": 2017,
                "price": 59.01
            },
            {
                "month": "February",
                "year": 2017,
                "price": 53.48
            },
            {
                "month": "March",
                "year": 2017,
                "price": 46.6
            },
            {
                "month": "April",
                "year": 2017,
                "price": 62.91
            },
            {
                "month": "May",
                "year": 2017,
                "price": 66.61
            },
            {
                "month": "June",
                "year": 2017,
                "price": 71.34
            },
            {
                "month": "July",
                "year": 2017,
                "price": 76.39
            },
            {
                "month": "August",
                "year": 2017,
                "price": 41.52
            },
            {
                "month": "September",
                "year": 2017,
                "price": 49.95
            },
            {
                "month": "October",
                "year": 2017,
                "price": 74.63
            },
            {
                "month": "November",
                "year": 2017,
                "price": 78.37
            },
            {
                "month": "December",
                "year": 2017,
                "price": 43.04
            }
        ],
        "2018": [
            {
                "month": "January",
                "year": 2018,
                "price": 48.19
            },
            {
                "month": "February",
                "year": 2018,
                "price": 63.63
            },
            {
                "month": "March",
                "year": 2018,
                "price": 45.07
            },
            {
                "month": "April",
                "year": 2018,
                "price": 44.49
            },
            {
                "month": "May",
                "year": 2018,
                "price": 68.83
            },
            {
                "month": "June",
                "year": 2018,
                "price": 60.25
            },
            {
                "month": "July",
                "year": 2018,
                "price": 44.53
            },
            {
                "month": "August",
                "year": 2018,
                "price": 42.57
            },
            {
                "month": "September",
                "year": 2018,
                "price": 66.68
            },
            {
                "month": "October",
                "year": 2018,
                "price": 61.27
            },
            {
                "month": "November",
                "year": 2018,
                "price": 32.91
            },
            {
                "month": "December",
                "year": 2018,
                "price": 68.86
            }
        ],
        "2019": [
            {
                "month": "January",
                "year": 2019,
                "price": 33.2
            },
            {
                "month": "February",
                "year": 2019,
                "price": 64.42
            },
            {
                "month": "March",
                "year": 2019,
                "price": 72.64
            },
            {
                "month": "April",
                "year": 2019,
                "price": 49.23
            },
            {
                "month": "May",
                "year": 2019,
                "price": 70.41
            },
            {
                "month": "June",
                "year": 2019,
                "price": 56.84
            },
            {
                "month": "July",
                "year": 2019,
                "price": 34.31
            },
            {
                "month": "August",
                "year": 2019,
                "price": 54.96
            },
            {
                "month": "September",
                "year": 2019,
                "price": 33.91
            },
            {
                "month": "October",
                "year": 2019,
                "price": 67.77
            },
            {
                "month": "November",
                "year": 2019,
                "price": 43.69
            },
            {
                "month": "December",
                "year": 2019,
                "price": 65.22
            }
        ],
        "2020": [
            {
                "month": "January",
                "year": 2020,
                "price": 67.87
            },
            {
                "month": "February",
                "year": 2020,
                "price": 36.2
            },
            {
                "month": "March",
                "year": 2020,
                "price": 37.39
            },
            {
                "month": "April",
                "year": 2020,
                "price": 78.67
            },
            {
                "month": "May",
                "year": 2020,
                "price": 65.94
            },
            {
                "month": "June",
                "year": 2020,
                "price": 75.49
            },
            {
                "month": "July",
                "year": 2020,
                "price": 47.94
            },
            {
                "month": "August",
                "year": 2020,
                "price": 37.83
            },
            {
                "month": "September",
                "year": 2020,
                "price": 51.7
            },
            {
                "month": "October",
                "year": 2020,
                "price": 43.21
            },
            {
                "month": "November",
                "year": 2020,
                "price": 57.77
            },
            {
                "month": "December",
                "year": 2020,
                "price": 52.6
            }
        ],
        "2024": [
            {
                "month": "January",
                "year": 2024,
                "price": 44.16
            },
            {
                "month": "February",
                "year": 2024,
                "price": 44.26
            },
            {
                "month": "March",
                "year": 2024,
                "price": 44.31
            },
            {
                "month": "April",
                "year": 2024,
                "price": 44.33
            },
            {
                "month": "May",
                "year": 2024,
                "price": 44.31
            },
            {
                "month": "June",
                "year": 2024,
                "price": 44.29
            },
            {
                "month": "July",
                "year": 2024,
                "price": 44.25
            },
            {
                "month": "August",
                "year": 2024,
                "price": 44.2
            },
            {
                "month": "September",
                "year": 2024,
                "price": 44.15
            },
            {
                "month": "October",
                "year": 2024,
                "price": 44.1
            },
            {
                "month": "November",
                "year": 2024,
                "price": 44.05
            },
            {
                "month": "December",
                "year": 2024,
                "price": 44.0
            }
        ],
        "2025": [
            {
                "month": "January",
                "year": 2025,
                "price": 44.16
            },
            {
                "month": "February",
                "year": 2025,
                "price": 44.26
            },
            {
                "month": "March",
                "year": 2025,
                "price": 44.31
            },
            {
                "month": "April",
                "year": 2025,
                "price": 44.33
            },
            {
                "month": "May",
                "year": 2025,
                "price": 44.31
            },
            {
                "month": "June",
                "year": 2025,
                "price": 44.29
            },
            {
                "month": "July",
                "year": 2025,
                "price": 44.25
            },
            {
                "month": "August",
                "year": 2025,
                "price": 44.2
            },
            {
                "month": "September",
                "year": 2025,
                "price": 44.15
            },
            {
                "month": "October",
                "year": 2025,
                "price": 44.1
            },
            {
                "month": "November",
                "year": 2025,
                "price": 44.05
            },
            {
                "month": "December",
                "year": 2025,
                "price": 44.0
            }
        ],
        "2026": [
            {
                "month": "January",
                "year": 2026,
                "price": 44.16
            },
            {
                "month": "February",
                "year": 2026,
                "price": 44.26
            },
            {
                "month": "March",
                "year": 2026,
                "price": 44.31
            },
            {
                "month": "April",
                "year": 2026,
                "price": 44.33
            },
            {
                "month": "May",
                "year": 2026,
                "price": 44.31
            },
            {
                "month": "June",
                "year": 2026,
                "price": 44.29
            },
            {
                "month": "July",
                "year": 2026,
                "price": 44.25
            },
            {
                "month": "August",
                "year": 2026,
                "price": 44.2
            },
            {
                "month": "September",
                "year": 2026,
                "price": 44.15
            },
            {
                "month": "October",
                "year": 2026,
                "price": 44.1
            },
            {
                "month": "November",
                "year": 2026,
                "price": 44.05
            },
            {
                "month": "December",
                "year": 2026,
                "price": 44.0
            }
        ]
    },
    "premium": {
        "2015": [
            {
                "month": "January",
                "year": 2015,
                "price": 53.36
            },
            {
                "month": "February",
                "year": 2015,
                "price": 40.21
            },
            {
                "month": "March",
                "year": 2015,
                "price": 40.38
            },
            {
                "month": "April",
                "year": 2015,
                "price": 52.69
            },
            {
                "month": "May",
                "year": 2015,
                "price": 69.98
            },
            {
                "month": "June",
                "year": 2015,
                "price": 67.41
            },
            {
                "month": "July",
                "year": 2015,
                "price": 71.99
            },
            {
                "month": "August",
                "year": 2015,
                "price": 47.91
            },
            {
                "month": "September",
                "year": 2015,
                "price": 63.5
            },
            {
                "month": "October",
                "year": 2015,
                "price": 36.35
            },
            {
                "month": "November",
                "year": 2015,
                "price": 40.79
            },
            {
                "month": "December",
                "year": 2015,
                "price": 47.07
            }
        ],
        "2016": [
            {
                "month": "January",
                "year": 2016,
                "price": 64.37
            },
            {
                "month": "February",
                "year": 2016,
                "price": 62.24
            },
            {
                "month": "March",
                "year": 2016,
                "price": 60.21
            },
            {
                "month": "April",
                "year": 2016,
                "price": 72.77
            },
            {
                "month": "May",
                "year": 2016,
                "price": 48.18
            },
            {
                "month": "June",
                "year": 2016,
                "price": 52.4
            },
            {
                "month": "July",
                "year": 2016,
                "price": 76.47
            },
            {
                "month": "August",
                "year": 2016,
                "price": 52.38
            },
            {
                "month": "September",
                "year": 2016,
                "price": 42.19
            },
            {
                "month": "October",
                "year": 2016,
                "price": 69.67
            },
            {
                "month": "November",
                "year": 2016,
                "price": 53.51
            },
            {
                "month": "December",
                "year": 2016,
                "price": 69.11
            }
        ],
        "2017": [
            {
                "month": "January",
                "year": 2017,
                "price": 70.87
            },
            {
                "month": "February",
                "year": 2017,
                "price": 57.96
            },
            {
                "month": "March",
                "year": 2017,
                "price": 76.46
            },
            {
                "month": "April",
                "year": 2017,
                "price": 78.31
            },
            {
                "month": "May",
                "year": 2017,
                "price": 33.53
            },
            {
                "month": "June",
                "year": 2017,
                "price": 78.37
            },
            {
                "month": "July",
                "year": 2017,
                "price": 73.72
            },
            {
                "month": "August",
                "year": 2017,
                "price": 63.85
            },
            {
                "month": "September",
                "year": 2017,
                "price": 68.79
            },
            {
                "month": "October",
                "year": 2017,
                "price": 52.87
            },
            {
                "month": "November",
                "year": 2017,
                "price": 37.88
            },
            {
                "month": "December",
                "year": 2017,
                "price": 61.24
            }
        ],
        "2018": [
            {
                "month": "January",
                "year": 2018,
                "price": 45.1
            },
            {
                "month": "February",
                "year": 2018,
                "price": 37.22
            },
            {
                "month": "March",
                "year": 2018,
                "price": 59.19
            },
            {
                "month": "April",
                "year": 2018,
                "price": 41.54
            },
            {
                "month": "May",
                "year": 2018,
                "price": 75.27
            },
            {
                "month": "June",
                "year": 2018,
                "price": 66.99
            },
            {
                "month": "July",
                "year": 2018,
                "price": 77.63
            },
            {
                "month": "August",
                "year": 2018,
                "price": 61.58
            },
            {
                "month": "September",
                "year": 2018,
                "price": 44.45
            },
            {
                "month": "October",
                "year": 2018,
                "price": 79.37
            },
            {
                "month": "November",
                "year": 2018,
                "price": 38.72
            },
            {
                "month": "December",
                "year": 2018,
                "price": 70.07
            }
        ],
        "2019": [
            {
                "month": "January",
                "year": 2019,
                "price": 54.23
            },
            {
                "month": "February",
                "year": 2019,
                "price": 51.51
            },
            {
                "month": "March",
                "year": 2019,
                "price": 61.52
            },
            {
                "month": "April",
                "year": 2019,
                "price": 37.74
            },
            {
                "month": "May",
                "year": 2019,
                "price": 43.62
            },
            {
                "month": "June",
                "year": 2019,
                "price": 56.99
            },
            {
                "month": "July",
                "year": 2019,
                "price": 41.76
            },
            {
                "month": "August",
                "year": 2019,
                "price": 77.92
            },
            {
                "month": "September",
                "year": 2019,
                "price": 33.13
            },
            {
                "month": "October",
                "year": 2019,
                "price": 43.43
            },
            {
                "month": "November",
                "year": 2019,
                "price": 44.57
            },
            {
                "month": "December",
                "year": 2019,
                "price": 60.31
            }
        ],
        "2020": [
            {
                "month": "January",
                "year": 2020,
                "price": 50.05
            },
            {
                "month": "February",
                "year": 2020,
                "price": 75.59
            },
            {
                "month": "March",
                "year": 2020,
                "price": 62.15
            },
            {
                "month": "April",
                "year": 2020,
                "price": 32.26
            },
            {
                "month": "May",
                "year": 2020,
                "price": 70.13
            },
            {
                "month": "June",
                "year": 2020,
                "price": 59.69
            },
            {
                "month": "July",
                "year": 2020,
                "price": 38.67
            },
            {
                "month": "August",
                "year": 2020,
                "price": 70.82
            },
            {
                "month": "September",
                "year": 2020,
                "price": 77.9
            },
            {
                "month": "October",
                "year": 2020,
                "price": 48.87
            },
            {
                "month": "November",
                "year": 2020,
                "price": 57.33
            },
            {
                "month": "December",
                "year": 2020,
                "price": 75.15
            }
        ],
        "2024": [
            {
                "month": "January",
                "year": 2024,
                "price": 44.77
            },
            {
                "month": "February",
                "year": 2024,
                "price": 44.99
            },
            {
                "month": "March",
                "year": 2024,
                "price": 45.11
            },
            {
                "month": "April",
                "year": 2024,
                "price": 45.16
            },
            {
                "month": "May",
                "year": 2024,
                "price": 45.16
            },
            {
                "month": "June",
                "year": 2024,
                "price": 45.13
            },
            {
                "month": "July",
                "year": 2024,
                "price": 45.07
            },
            {
                "month": "August",
                "year": 2024,
                "price": 44.99
            },
            {
                "month": "September",
                "year": 2024,
                "price": 44.91
            },
            {
                "month": "October",
                "year": 2024,
                "price": 44.82
            },
            {
                "month": "November",
                "year": 2024,
                "price": 44.73
            },
            {
                "month": "December",
                "year": 2024,
                "price": 44.64
            }
        ],
        "2025": [
            {
                "month": "January",
                "year": 2025,
                "price": 44.77
            },
            {
                "month": "February",
                "year": 2025,
                "price": 44.99
            },
            {
                "month": "March",
                "year": 2025,
                "price": 45.11
            },
            {
                "month": "April",
                "year": 2025,
                "price": 45.16
            },
            {
                "month": "May",
                "year": 2025,
                "price": 45.16
            },
            {
                "month": "June",
                "year": 2025,
                "price": 45.13
            },
            {
                "month": "July",
                "year": 2025,
                "price": 45.07
            },
            {
                "month": "August",
                "year": 2025,
                "price": 44.99
            },
            {
                "month": "September",
                "year": 2025,
                "price": 44.91
            },
            {
                "month": "October",
                "year": 2025,
                "price": 44.82
            },
            {
                "month": "November",
                "year": 2025,
                "price": 44.73
            },
            {
                "month": "December",
                "year": 2025,
                "price": 44.64
            }
        ],
        "2026": [
            {
                "month": "January",
                "year": 2026,
                "price": 44.77
            },
            {
                "month": "February",
                "year": 2026,
                "price": 44.99
            },
            {
                "month": "March",
                "year": 2026,
                "price": 45.11
            },
            {
                "month": "April",
                "year": 2026,
                "price": 45.16
            },
            {
                "month": "May",
                "year": 2026,
                "price": 45.16
            },
            {
                "month": "June",
                "year": 2026,
                "price": 45.13
            },
            {
                "month": "July",
                "year": 2026,
                "price": 45.07
            },
            {
                "month": "August",
                "year": 2026,
                "price": 44.99
            },
            {
                "month": "September",
                "year": 2026,
                "price": 44.91
            },
            {
                "month": "October",
                "year": 2026,
                "price": 44.82
            },
            {
                "month": "November",
                "year": 2026,
                "price": 44.73
            },
            {
                "month": "December",
                "year": 2026,
                "price": 44.64
            }
        ]
    },
    "special": {
        "2015": [
            {
                "month": "January",
                "year": 2015,
                "price": 40.19
            },
            {
                "month": "February",
                "year": 2015,
                "price": 39.65
            },
            {
                "month": "March",
                "year": 2015,
                "price": 39.32
            },
            {
                "month": "April",
                "year": 2015,
                "price": 50.1
            },
            {
                "month": "May",
                "year": 2015,
                "price": 37.89
            },
            {
                "month": "June",
                "year": 2015,
                "price": 42.53
            },
            {
                "month": "July",
                "year": 2015,
                "price": 48.23
            },
            {
                "month": "August",
                "year": 2015,
                "price": 45.41
            },
            {
                "month": "September",
                "year": 2015,
                "price": 52.57
            },
            {
                "month": "October",
                "year": 2015,
                "price": 48.56
            },
            {
                "month": "November",
                "year": 2015,
                "price": 41.03
            },
            {
                "month": "December",
                "year": 2015,
                "price": 41.16
            }
        ],
        "2016": [
            {
                "month": "January",
                "year": 2016,
                "price": 44.57
            },
            {
                "month": "February",
                "year": 2016,
                "price": 53.38
            },
            {
                "month": "March",
                "year": 2016,
                "price": 72.04
            },
            {
                "month": "April",
                "year": 2016,
                "price": 47.9
            },
            {
                "month": "May",
                "year": 2016,
                "price": 41.16
            },
            {
                "month": "June",
                "year": 2016,
                "price": 42.91
            },
            {
                "month": "July",
                "year": 2016,
                "price": 47.24
            },
            {
                "month": "August",
                "year": 2016,
                "price": 66.38
            },
            {
                "month": "September",
                "year": 2016,
                "price": 70.14
            },
            {
                "month": "October",
                "year": 2016,
                "price": 45.09
            },
            {
                "month": "November",
                "year": 2016,
                "price": 53.18
            },
            {
                "month": "December",
                "year": 2016,
                "price": 39.92
            }
        ],
        "2017": [
            {
                "month": "January",
                "year": 2017,
                "price": 74.81
            },
            {
                "month": "February",
                "year": 2017,
                "price": 55.6
            },
            {
                "month": "March",
                "year": 2017,
                "price": 48.32
            },
            {
                "month": "April",
                "year": 2017,
                "price": 30.4
            },
            {
                "month": "May",
                "year": 2017,
                "price": 69.28
            },
            {
                "month": "June",
                "year": 2017,
                "price": 31.63
            },
            {
                "month": "July",
                "year": 2017,
                "price": 70.72
            },
            {
                "month": "August",
                "year": 2017,
                "price": 40.83
            },
            {
                "month": "September",
                "year": 2017,
                "price": 49.33
            },
            {
                "month": "October",
                "year": 2017,
                "price": 57.88
            },
            {
                "month": "November",
                "year": 2017,
                "price": 42.05
            },
            {
                "month": "December",
                "year": 2017,
                "price": 76.85
            }
        ],
        "2018": [
            {
                "month": "January",
                "year": 2018,
                "price": 31.42
            },
            {
                "month": "February",
                "year": 2018,
                "price": 31.61
            },
            {
                "month": "March",
                "year": 2018,
                "price": 63.31
            },
            {
                "month": "April",
                "year": 2018,
                "price": 69.35
            },
            {
                "month": "May",
                "year": 2018,
                "price": 51.95
            },
            {
                "month": "June",
                "year": 2018,
                "price": 63.31
            },
            {
                "month": "July",
                "year": 2018,
                "price": 64.39
            },
            {
                "month": "August",
                "year": 2018,
                "price": 76.6
            },
            {
                "month": "September",
                "year": 2018,
                "price": 41.2
            },
            {
                "month": "October",
                "year": 2018,
                "price": 72.2
            },
            {
                "month": "November",
                "year": 2018,
                "price": 76.24
            },
            {
                "month": "December",
                "year": 2018,
                "price": 48.78
            }
        ],
        "2019": [
            {
                "month": "January",
                "year": 2019,
                "price": 37.4
            },
            {
                "month": "February",
                "year": 2019,
                "price": 45.13
            },
            {
                "month": "March",
                "year": 2019,
                "price": 50.53
            },
            {
                "month": "April",
                "year": 2019,
                "price": 44.1
            },
            {
                "month": "May",
                "year": 2019,
                "price": 50.76
            },
            {
                "month": "June",
                "year": 2019,
                "price": 61.0
            },
            {
                "month": "July",
                "year": 2019,
                "price": 76.44
            },
            {
                "month": "August",
                "year": 2019,
                "price": 71.02
            },
            {
                "month": "September",
                "year": 2019,
                "price": 77.43
            },
            {
                "month": "October",
                "year": 2019,
                "price": 39.96
            },
            {
                "month": "November",
                "year": 2019,
                "price": 44.37
            },
            {
                "month": "December",
                "year": 2019,
                "price": 30.04
            }
        ],
        "2020": [
            {
                "month": "January",
                "year": 2020,
                "price": 69.11
            },
            {
                "month": "February",
                "year": 2020,
                "price": 62.64
            },
            {
                "month": "March",
                "year": 2020,
                "price": 59.02
            },
            {
                "month": "April",
                "year": 2020,
                "price": 52.71
            },
            {
                "month": "May",
                "year": 2020,
                "price": 66.4
            },
            {
                "month": "June",
                "year": 2020,
                "price": 36.58
            },
            {
                "month": "July",
                "year": 2020,
                "price": 44.4
            },
            {
                "month": "August",
                "year": 2020,
                "price": 43.69
            },
            {
                "month": "September",
                "year": 2020,
                "price": 63.0
            },
            {
                "month": "October",
                "year": 2020,
                "price": 52.5
            },
            {
                "month": "November",
                "year": 2020,
                "price": 37.11
            },
            {
                "month": "December",
                "year": 2020,
                "price": 33.75
            }
        ],
        "2024": [
            {
                "month": "January",
                "year": 2024,
                "price": 53.56
            },
            {
                "month": "February",
                "year": 2024,
                "price": 53.46
            },
            {
                "month": "March",
                "year": 2024,
                "price": 53.33
            },
            {
                "month": "April",
                "year": 2024,
                "price": 53.17
            },
            {
                "month": "May",
                "year": 2024,
                "price": 53.0
            },
            {
                "month": "June",
                "year": 2024,
                "price": 52.83
            },
            {
                "month": "July",
                "year": 2024,
                "price": 52.65
            },
            {
                "month": "August",
                "year": 2024,
                "price": 52.47
            },
            {
                "month": "September",
                "year": 2024,
                "price": 52.29
            },
            {
                "month": "October",
                "year": 2024,
                "price": 52.11
            },
            {
                "month": "November",
                "year": 2024,
                "price": 51.93
            },
            {
                "month": "December",
                "year": 2024,
                "price": 51.76
            }
        ],
        "2025": [
            {
                "month": "January",
                "year": 2025,
                "price": 53.56
            },
            {
                "month": "February",
                "year": 2025,
                "price": 53.46
            },
            {
                "month": "March",
                "year": 2025,
                "price": 53.33
            },
            {
                "month": "April",
                "year": 2025,
                "price": 53.17
            },
            {
                "month": "May",
                "year": 2025,
                "price": 53.0
            },
            {
                "month": "June",
                "year": 2025,
                "price": 52.83
            },
            {
                "month": "July",
                "year": 2025,
                "price": 52.65
            },
            {
                "month": "August",
                "year": 2025,
                "price": 52.47
            },
            {
                "month": "September",
                "year": 2025,
                "price": 52.29
            },
            {
                "month": "October",
                "year": 2025,
                "price": 52.11
            },
            {
                "month": "November",
                "year": 2025,
                "price": 51.93
            },
            {
                "month": "December",
                "year": 2025,
                "price": 51.76
            }
        ],
        "2026": [
            {
                "month": "January",
                "year": 2026,
                "price": 53.56
            },
            {
                "month": "February",
                "year": 2026,
                "price": 53.46
            },
            {
                "month": "March",
                "year": 2026,
                "price": 53.33
            },
            {
                "month": "April",
                "year": 2026,
                "price": 53.17
            },
            {
                "month": "May",
                "year": 2026,
                "price": 53.0
            },
            {
                "month": "June",
                "year": 2026,
                "price": 52.83
            },
            {
                "month": "July",
                "year": 2026,
                "price": 52.65
            },
            {
                "month": "August",
                "year": 2026,
                "price": 52.47
            },
            {
                "month": "September",
                "year": 2026,
                "price": 52.29
            },
            {
                "month": "October",
                "year": 2026,
                "price": 52.11
            },
            {
                "month": "November",
                "year": 2026,
                "price": 51.93
            },
            {
                "month": "December",
                "year": 2026,
                "price": 51.76
            }
        ]
    },
    "well milled": {
        "2015": [
            {
                "month": "January",
                "year": 2015,
                "price": 39.41
            },
            {
                "month": "February",
                "year": 2015,
                "price": 49.65
            },
            {
                "month": "March",
                "year": 2015,
                "price": 62.37
            },
            {
                "month": "April",
                "year": 2015,
                "price": 51.43
            },
            {
                "month": "May",
                "year": 2015,
                "price": 75.4
            },
            {
                "month": "June",
                "year": 2015,
                "price": 39.75
            },
            {
                "month": "July",
                "year": 2015,
                "price": 78.42
            },
            {
                "month": "August",
                "year": 2015,
                "price": 77.16
            },
            {
                "month": "September",
                "year": 2015,
                "price": 62.99
            },
            {
                "month": "October",
                "year": 2015,
                "price": 45.08
            },
            {
                "month": "November",
                "year": 2015,
                "price": 72.64
            },
            {
                "month": "December",
                "year": 2015,
                "price": 76.47
            }
        ],
        "2016": [
            {
                "month": "January",
                "year": 2016,
                "price": 55.3
            },
            {
                "month": "February",
                "year": 2016,
                "price": 75.22
            },
            {
                "month": "March",
                "year": 2016,
                "price": 66.0
            },
            {
                "month": "April",
                "year": 2016,
                "price": 33.95
            },
            {
                "month": "May",
                "year": 2016,
                "price": 68.4
            },
            {
                "month": "June",
                "year": 2016,
                "price": 68.95
            },
            {
                "month": "July",
                "year": 2016,
                "price": 74.04
            },
            {
                "month": "August",
                "year": 2016,
                "price": 35.33
            },
            {
                "month": "September",
                "year": 2016,
                "price": 79.12
            },
            {
                "month": "October",
                "year": 2016,
                "price": 78.02
            },
            {
                "month": "November",
                "year": 2016,
                "price": 35.0
            },
            {
                "month": "December",
                "year": 2016,
                "price": 41.41
            }
        ],
        "2017": [
            {
                "month": "January",
                "year": 2017,
                "price": 43.75
            },
            {
                "month": "February",
                "year": 2017,
                "price": 41.84
            },
            {
                "month": "March",
                "year": 2017,
                "price": 64.84
            },
            {
                "month": "April",
                "year": 2017,
                "price": 49.25
            },
            {
                "month": "May",
                "year": 2017,
                "price": 50.23
            },
            {
                "month": "June",
                "year": 2017,
                "price": 46.93
            },
            {
                "month": "July",
                "year": 2017,
                "price": 32.67
            },
            {
                "month": "August",
                "year": 2017,
                "price": 78.65
            },
            {
                "month": "September",
                "year": 2017,
                "price": 66.54
            },
            {
                "month": "October",
                "year": 2017,
                "price": 47.73
            },
            {
                "month": "November",
                "year": 2017,
                "price": 79.3
            },
            {
                "month": "December",
                "year": 2017,
                "price": 71.15
            }
        ],
        "2018": [
            {
                "month": "January",
                "year": 2018,
                "price": 72.12
            },
            {
                "month": "February",
                "year": 2018,
                "price": 48.62
            },
            {
                "month": "March",
                "year": 2018,
                "price": 61.77
            },
            {
                "month": "April",
                "year": 2018,
                "price": 38.46
            },
            {
                "month": "May",
                "year": 2018,
                "price": 66.79
            },
            {
                "month": "June",
                "year": 2018,
                "price": 55.86
            },
            {
                "month": "July",
                "year": 2018,
                "price": 30.95
            },
            {
                "month": "August",
                "year": 2018,
                "price": 53.17
            },
            {
                "month": "September",
                "year": 2018,
                "price": 37.02
            },
            {
                "month": "October",
                "year": 2018,
                "price": 56.67
            },
            {
                "month": "November",
                "year": 2018,
                "price": 53.2
            },
            {
                "month": "December",
                "year": 2018,
                "price": 52.1
            }
        ],
        "2019": [
            {
                "month": "January",
                "year": 2019,
                "price": 72.8
            },
            {
                "month": "February",
                "year": 2019,
                "price": 43.74
            },
            {
                "month": "March",
                "year": 2019,
                "price": 53.43
            },
            {
                "month": "April",
                "year": 2019,
                "price": 55.67
            },
            {
                "month": "May",
                "year": 2019,
                "price": 72.02
            },
            {
                "month": "June",
                "year": 2019,
                "price": 73.99
            },
            {
                "month": "July",
                "year": 2019,
                "price": 58.54
            },
            {
                "month": "August",
                "year": 2019,
                "price": 43.26
            },
            {
                "month": "September",
                "year": 2019,
                "price": 32.98
            },
            {
                "month": "October",
                "year": 2019,
                "price": 69.59
            },
            {
                "month": "November",
                "year": 2019,
                "price": 49.28
            },
            {
                "month": "December",
                "year": 2019,
                "price": 31.78
            }
        ],
        "2020": [
            {
                "month": "January",
                "year": 2020,
                "price": 63.75
            },
            {
                "month": "February",
                "year": 2020,
                "price": 78.35
            },
            {
                "month": "March",
                "year": 2020,
                "price": 76.43
            },
            {
                "month": "April",
                "year": 2020,
                "price": 62.12
            },
            {
                "month": "May",
                "year": 2020,
                "price": 35.51
            },
            {
                "month": "June",
                "year": 2020,
                "price": 51.79
            },
            {
                "month": "July",
                "year": 2020,
                "price": 76.81
            },
            {
                "month": "August",
                "year": 2020,
                "price": 35.53
            },
            {
                "month": "September",
                "year": 2020,
                "price": 51.73
            },
            {
                "month": "October",
                "year": 2020,
                "price": 64.75
            },
            {
                "month": "November",
                "year": 2020,
                "price": 70.0
            },
            {
                "month": "December",
                "year": 2020,
                "price": 70.5
            }
        ],
        "2024": [
            {
                "month": "January",
                "year": 2024,
                "price": 48.53
            },
            {
                "month": "February",
                "year": 2024,
                "price": 48.46
            },
            {
                "month": "March",
                "year": 2024,
                "price": 48.37
            },
            {
                "month": "April",
                "year": 2024,
                "price": 48.28
            },
            {
                "month": "May",
                "year": 2024,
                "price": 48.19
            },
            {
                "month": "June",
                "year": 2024,
                "price": 48.09
            },
            {
                "month": "July",
                "year": 2024,
                "price": 48.0
            },
            {
                "month": "August",
                "year": 2024,
                "price": 47.91
            },
            {
                "month": "September",
                "year": 2024,
                "price": 47.83
            },
            {
                "month": "October",
                "year": 2024,
                "price": 47.75
            },
            {
                "month": "November",
                "year": 2024,
                "price": 47.67
            },
            {
                "month": "December",
                "year": 2024,
                "price": 47.6
            }
        ],
        "2025": [
            {
                "month": "January",
                "year": 2025,
                "price": 48.53
            },
            {
                "month": "February",
                "year": 2025,
                "price": 48.46
            },
            {
                "month": "March",
                "year": 2025,
                "price": 48.37
            },
            {
                "month": "April",
                "year": 2025,
                "price": 48.28
            },
            {
                "month": "May",
                "year": 2025,
                "price": 48.19
            },
            {
                "month": "June",
                "year": 2025,
                "price": 48.09
            },
            {
                "month": "July",
                "year": 2025,
                "price": 48.0
            },
            {
                "month": "August",
                "year": 2025,
                "price": 47.91
            },
            {
                "month": "September",
                "year": 2025,
                "price": 47.83
            },
            {
                "month": "October",
                "year": 2025,
                "price": 47.75
            },
            {
                "month": "November",
                "year": 2025,
                "price": 47.67
            },
            {
                "month": "December",
                "year": 2025,
                "price": 47.6
            }
        ],
        "2026": [
            {
                "month": "January",
                "year": 2026,
                "price": 48.53
            },
            {
                "month": "February",
                "year": 2026,
                "price": 48.46
            },
            {
                "month": "March",
                "year": 2026,
                "price": 48.37
            },
            {
                "month": "April",
                "year": 2026,
                "price": 48.28
            },
            {
                "month": "May",
                "year": 2026,
                "price": 48.19
            },
            {
                "month": "June",
                "year": 2026,
                "price": 48.09
            },
            {
                "month": "July",
                "year": 2026,
                "price": 48.0
            },
            {
                "month": "August",
                "year": 2026,
                "price": 47.91
            },
            {
                "month": "September",
                "year": 2026,
                "price": 47.83
            },
            {
                "month": "October",
                "year": 2026,
                "price": 47.75
            },
            {
                "month": "November",
                "year": 2026,
                "price": 47.67
            },
            {
                "month": "December",
                "year": 2026,
                "price": 47.6
            }
        ]
    }
}